audio_scribe/__init__.py
audio_scribe/auth.py
audio_scribe/config.py
audio_scribe/models.py
audio_scribe/transcriber.py
audio_scribe/utils.py
audio_scribe-0.1.6.dist-info/licenses/LICENSE
audio_scribe-0.1.6.dist-info/METADATA
audio_scribe-0.1.6.dist-info/WHEEL
audio_scribe-0.1.6.dist-info/entry_points.txt
audio_scribe-0.1.6.dist-info/top_level.txt
audio_scribe-0.1.6.dist-info/RECORD
