Metadata-Version: 2.4
Name: audio_scribe
Version: 0.1.6
Summary: A command-line tool for audio transcription with Whisper and Pyannote.
Home-page: https://gitlab.genomicops.cloud/innovation-hub/audio-scribe
Author: Gurasis Osahan
Author-email: contact@genomicops.com
License: Apache-2.0
Project-URL: Source, https://gitlab.genomicops.cloud/innovation-hub/audio-scribe
Project-URL: Tracker, https://gitlab.genomicops.cloud/innovation-hub/audio-scribe/-/issues
Keywords: whisper pyannote transcription audio diarization
Classifier: Development Status :: 3 - Alpha
Classifier: Intended Audience :: Developers
Classifier: Intended Audience :: Science/Research
Classifier: Topic :: Multimedia :: Sound/Audio
Classifier: Topic :: Scientific/Engineering :: Artificial Intelligence
Classifier: License :: OSI Approved :: Apache Software License
Classifier: Programming Language :: Python :: 3
Classifier: Programming Language :: Python :: 3.8
Classifier: Programming Language :: Python :: 3.9
Classifier: Programming Language :: Python :: 3.10
Classifier: Operating System :: OS Independent
Requires-Python: >=3.8
License-File: LICENSE
Requires-Dist: torch>=2.7.1
Requires-Dist: openai-whisper
Requires-Dist: pyannote.audio>=3.3.2
Requires-Dist: pytorch-lightning
Requires-Dist: keyring>=25.6.0
Requires-Dist: cryptography
Requires-Dist: alive-progress>=3.2.0
Requires-Dist: psutil>=7.0.0
Requires-Dist: GPUtil>=1.4.0
Dynamic: author
Dynamic: author-email
Dynamic: classifier
Dynamic: description
Dynamic: description-content-type
Dynamic: home-page
Dynamic: keywords
Dynamic: license
Dynamic: license-file
Dynamic: project-url
Dynamic: requires-dist
Dynamic: requires-python
Dynamic: summary
